{"hnz": "乏", "trd": null, "isTrd": false, "cmp": ["丿 (slash)", "之 ((literary equivalent of 的)/(subor. part.)/him/her/it)"], "mng": ["short of, tired"], "pyn": ["fá"], "exm": [{"cur": "乏", "trd": null, "mng": "short of, tired", "pyn": "fá"}, {"cur": "缺乏", "trd": null, "mng": "to lack, to be short of, lack, shortage", "pyn": "quē fá"}, {"cur": "疲乏", "trd": null, "mng": "tired, weary", "pyn": "pí fá"}, {"cur": "乏味", "trd": null, "mng": "tedious", "pyn": "fá wèi"}, {"cur": "匮乏", "trd": "匱乏", "mng": "to be deficient in sth, to be short of sth (supplies, money etc)", "pyn": "kuì fá"}, {"cur": "贫乏", "trd": "貧乏", "mng": "impoverished, lacking, deficient, limited, meager, impoverishment, lack, deficiency", "pyn": "pín fá"}, {"cur": "不乏", "trd": null, "mng": "there is no lack of", "pyn": "bù fá"}, {"cur": "缺乏症", "trd": null, "mng": "clinical deficiency", "pyn": "quē fá zhèng"}, {"cur": "解乏", "trd": null, "mng": "to relieve tiredness, to freshen up", "pyn": "jiě fá"}, {"cur": "单调乏味", "trd": "單調乏味", "mng": "monotonous, dull, tedious (idiom)", "pyn": "dān diào fá wèi"}, {"cur": "欲振乏力", "trd": null, "mng": "to try to rouse oneself but lack the strength (idiom)", "pyn": "yù zhèn fá lì"}, {"cur": "乏燃料", "trd": null, "mng": "spent fuel", "pyn": "fá rán liào"}, {"cur": "人困马乏", "trd": "人困馬乏", "mng": "riders tired and horses weary, worn out, exhausted, spent, fatigued", "pyn": "rén kùn mǎ fá"}, {"cur": "承乏", "trd": null, "mng": "to accept a position on a provisional basis, in the absence of better qualified candidates (humble expr.)", "pyn": "chéng fá"}, {"cur": "语言匮乏", "trd": "語言匱乏", "mng": "language deficit (linguistics)", "pyn": "yǔ yán kuì fá"}, {"cur": "乏燃料棒", "trd": null, "mng": "spent fuel rods", "pyn": "fá rán liào bàng"}, {"cur": "无虞匮乏", "trd": "無虞匱乏", "mng": "no fear of deficiency, sufficient, abundant", "pyn": "wú yú kuì fá"}, {"cur": "乏燃料储存", "trd": "乏燃料儲存", "mng": "spent fuel storage", "pyn": "fá rán liào chǔ cún"}, {"cur": "勤劳不虞匮乏", "trd": "勤勞不虞匱乏", "mng": "Poverty is a stranger to industry. (idiom)", "pyn": "qín láo bù yú kuì fá"}, {"cur": "乏人照顾", "trd": "乏人照顧", "mng": "(of a person) left unattended, not cared for", "pyn": "fá rén zhào gù"}], "cur": "乏"}