{"hnz": "仅", "trd": "僅", "isTrd": false, "cmp": ["亻 (man)", "又 ((once) again/also/both... and.../again)"], "mng": ["barely, only, merely"], "pyn": ["jǐn"], "exm": [{"cur": "不仅", "trd": "不僅", "mng": "not only (this one), not just (...) but also", "pyn": "bù jǐn"}, {"cur": "仅供", "trd": "僅供", "mng": "only for", "pyn": "jǐn gōng"}, {"cur": "仅供参考", "trd": "僅供參考", "mng": "for reference only", "pyn": "jǐn gōng cān kǎo"}, {"cur": "仅仅", "trd": "僅僅", "mng": "barely, only, merely, only (this and nothing more)", "pyn": "jǐn jǐn"}, {"cur": "绝无仅有", "trd": "絕無僅有", "mng": "one and only (idiom); rarely seen, unique of its kind", "pyn": "jué wú jǐn yǒu"}, {"cur": "仅作参考", "trd": "僅作參考", "mng": "for reference only", "pyn": "jǐn zuò cān kǎo"}, {"cur": "不仅如此", "trd": "不僅如此", "mng": "not only that, but ...", "pyn": "bù jǐn rú cǐ"}, {"cur": "仅次于", "trd": "僅次于", "mng": "second only to..., (in second place) preceded only by...", "pyn": "jǐn cì yú"}, {"cur": "仅此而已", "trd": "僅此而已", "mng": "that's all, just this and nothing more", "pyn": "jǐn cǐ ér yǐ"}, {"cur": "硕果仅存", "trd": "碩果僅存", "mng": "only remaining of the great (idiom); one of the few greats extant", "pyn": "shuò guǒ jǐn cún"}], "cur": "仅"}