{"hnz": "企", "trd": null, "isTrd": false, "cmp": ["人 (man/person/people)", "止 (to stop/toe)"], "mng": ["to plan a project, to stand on tiptoe, Taiwan pr. [qi4], abbr. for 企業|企业[qi3 ye4]"], "pyn": ["qǐ"], "exm": [{"cur": "企", "trd": null, "mng": "to plan a project, to stand on tiptoe, Taiwan pr. [qi4], abbr. for 企業|企业[qi3 ye4]", "pyn": "qǐ"}, {"cur": "企业", "trd": "企業", "mng": "company, firm, enterprise, corporation", "pyn": "qǐ yè"}, {"cur": "企及", "trd": null, "mng": "to hope to reach, to strive for", "pyn": "qǐ jí"}, {"cur": "私企", "trd": null, "mng": "private enterprise, abbr. of 私營企業|私营企业[si1 ying2 qi3 ye4]", "pyn": "sī qǐ"}, {"cur": "企盼", "trd": null, "mng": "to expect, to look forward to, anxious for sth, to hope (to get sth)", "pyn": "qǐ pàn"}, {"cur": "企划", "trd": "企劃", "mng": "to plan, to lay out, to design", "pyn": "qǐ huà"}, {"cur": "企图", "trd": "企圖", "mng": "to attempt, to try, attempt", "pyn": "qǐ tú"}, {"cur": "国企", "trd": "國企", "mng": "state enterprise, (Tw) abbr. for 國際企業管理|国际企业管理, international business management (as a subject of study)", "pyn": "guó qǐ"}, {"cur": "企鹅", "trd": "企鵝", "mng": "penguin", "pyn": "qǐ é"}, {"cur": "外企", "trd": null, "mng": "foreign enterprise, company established in mainland China with direct investment from foreign entities or from investors in Taiwan, Macao or Hong Kong, abbr. for 外資企業|外资企业", "pyn": "wài qǐ"}, {"cur": "龙头企业", "trd": "龍頭企業", "mng": "key enterprises, leading enterprises", "pyn": "lóng tóu qǐ yè"}, {"cur": "企业管理", "trd": "企業管理", "mng": "business management (as a study)", "pyn": "qǐ yè guǎn lǐ"}, {"cur": "私营企业", "trd": "私營企業", "mng": "private business, opposite: state-owned enterprise 國有企業|国有企业[guo2 you3 qi3 ye4]", "pyn": "sī yíng qǐ yè"}, {"cur": "生产企业", "trd": "生產企業", "mng": "manufacturer", "pyn": "shēng chǎn qǐ yè"}, {"cur": "大型企业", "trd": "大型企業", "mng": "large scale industry, major industry", "pyn": "dà xíng qǐ yè"}, {"cur": "小型企业", "trd": "小型企業", "mng": "small business", "pyn": "xiǎo xíng qǐ yè"}, {"cur": "中小型企业", "trd": "中小型企業", "mng": "small or medium size enterprise (SME)", "pyn": "zhōng xiǎo xíng qǐ yè"}, {"cur": "企业集团", "trd": "企業集團", "mng": "industry association", "pyn": "qǐ yè jí tuán"}, {"cur": "小企业", "trd": "小企業", "mng": "small enterprise", "pyn": "xiǎo qǐ yè"}, {"cur": "国有企业", "trd": "國有企業", "mng": "nationalized business, state-owned business", "pyn": "guó yǒu qǐ yè"}], "cur": "企"}