{"hnz": "俭", "trd": "儉", "isTrd": false, "cmp": ["亻 (man)", "人 (man/person/people)", "亼 (Unknown)", "一 (one/1/single/a(n))", "佥 (all)", "小一 (Unknown)"], "mng": ["frugal, thrifty, needy"], "pyn": ["jiǎn"], "exm": [{"cur": "俭", "trd": "儉", "mng": "frugal, thrifty, needy", "pyn": "jiǎn"}, {"cur": "勤俭", "trd": "勤儉", "mng": "hardworking and frugal", "pyn": "qín jiǎn"}, {"cur": "节俭", "trd": "節儉", "mng": "frugal, economical", "pyn": "jié jiǎn"}, {"cur": "勤工俭学", "trd": "勤工儉學", "mng": "to work part time while studying, work-study program", "pyn": "qín gōng jiǎn xué"}, {"cur": "勤俭节约", "trd": "勤儉節約", "mng": "diligent and thrifty (idiom)", "pyn": "qín jiǎn jié yuē"}, {"cur": "省吃俭用", "trd": "省吃儉用", "mng": "to live frugally, to economize on food and clothing, to scrimp and save", "pyn": "shěng chī jiǎn yòng"}, {"cur": "俭用", "trd": "儉用", "mng": "to skimp, to be frugal", "pyn": "jiǎn yòng"}, {"cur": "俭朴", "trd": "儉朴", "mng": "plain and unadorned, thrifty and simple", "pyn": "jiǎn pǔ"}, {"cur": "克俭", "trd": "克儉", "mng": "thrift, economy", "pyn": "kè jiǎn"}, {"cur": "丰俭由人", "trd": "豐儉由人", "mng": "fancy or simple according to sb's budget (idiom)", "pyn": "fēng jiǎn yóu rén"}, {"cur": "克勤克俭", "trd": "克勤克儉", "mng": "to be industrious and frugal (idiom)", "pyn": "kè qín kè jiǎn"}, {"cur": "温良恭俭让", "trd": "溫良恭儉讓", "mng": "kindhearted and moderate (idiom); temperate and gentle", "pyn": "wēn liáng gōng jiǎn ràng"}, {"cur": "俭省", "trd": "儉省", "mng": "thrifty, sparing, economical", "pyn": "jiǎn shěng"}, {"cur": "俭约", "trd": "儉約", "mng": "sparing, economical", "pyn": "jiǎn yuē"}, {"cur": "奢入俭难", "trd": "奢入儉難", "mng": "it is hard to become frugal after becoming accustomed to luxury (idiom)", "pyn": "shē rù jiǎn nán"}, {"cur": "勤俭办学", "trd": "勤儉辦學", "mng": "to run a school diligently and thriftily", "pyn": "qín jiǎn bàn xué"}, {"cur": "勤俭建国", "trd": "勤儉建國", "mng": "to build up the country through thrift and hard work (idiom)", "pyn": "qín jiǎn jiàn guó"}, {"cur": "勤俭朴素", "trd": "勤儉樸素", "mng": "hardworking, thrifty, plain, and simple (idiom)", "pyn": "qín jiǎn pǔ sù"}, {"cur": "俭学", "trd": "儉學", "mng": "to deny oneself comforts in order to save money for one's education", "pyn": "jiǎn xué"}, {"cur": "省俭", "trd": "省儉", "mng": "frugal, economic, to scrimp and save", "pyn": "shěng jiǎn"}], "cur": "俭"}