{"hnz": "候", "trd": null, "isTrd": false, "cmp": [], "mng": ["to wait, to inquire after, to watch, season, climate, (old) period of five days"], "pyn": ["hòu"], "exm": [{"cur": "症候群", "trd": null, "mng": "syndrome", "pyn": "zhèng hòu qún"}, {"cur": "时候", "trd": "時候", "mng": "time, length of time, moment, period", "pyn": "shí hou"}, {"cur": "什么时候", "trd": "甚麼時候", "mng": "when?, at what time?", "pyn": "shén me shí hou"}, {"cur": "什么时候", "trd": "什麽時候", "mng": "variant of 甚麼時候|什么时候, when?, at what time?", "pyn": "shén me shí hou"}, {"cur": "有时候", "trd": "有時候", "mng": "sometimes", "pyn": "yǒu shí hou"}, {"cur": "全天候", "trd": null, "mng": "all-weather", "pyn": "quán tiān hòu"}, {"cur": "火候", "trd": null, "mng": "heat control, maturity, crucial moment", "pyn": "huǒ hòu"}, {"cur": "气候", "trd": "氣候", "mng": "climate, atmosphere, situation", "pyn": "qì hòu"}, {"cur": "候审", "trd": "候審", "mng": "awaiting trial", "pyn": "hòu shěn"}, {"cur": "等候", "trd": null, "mng": "to wait, to wait for", "pyn": "děng hòu"}], "cur": "候"}