{"hnz": "又", "trd": null, "isTrd": false, "cmp": [], "mng": ["(once) again, also, both... and..., and yet, (used for emphasis) anyway"], "pyn": ["yòu"], "exm": [{"cur": "又称", "trd": "又稱", "mng": "also known as", "pyn": "yòu chēng"}, {"cur": "又来了", "trd": "又來了", "mng": "Here we go again.", "pyn": "yòu lái le"}, {"cur": "又一次", "trd": null, "mng": "yet again, once again, once more", "pyn": "yòu yī cì"}, {"cur": "少之又少", "trd": null, "mng": "very few, very little", "pyn": "shǎo zhī yòu shǎo"}, {"cur": "一次又一次", "trd": null, "mng": "repeatedly, over and over again", "pyn": "yī cì yòu yī cì"}, {"cur": "一遍又一遍", "trd": null, "mng": "over and over", "pyn": "yī biàn yòu yī biàn"}, {"cur": "又名", "trd": null, "mng": "also known as, alternative name, to also be called", "pyn": "yòu míng"}, {"cur": "重又", "trd": null, "mng": "once again", "pyn": "chóng yòu"}, {"cur": "话又说回来", "trd": "話又說回來", "mng": "returning to our main topic,..., that said,..., again,..., in this connection, in passing, nevertheless,..., anyhow", "pyn": "huà yòu shuō huí lai"}, {"cur": "又红又肿", "trd": "又紅又腫", "mng": "to be red and swollen (idiom)", "pyn": "yòu hóng yòu zhǒng"}], "cur": "又"}