{"hnz": "嗝", "trd": null, "isTrd": false, "cmp": ["口 (mouth/(a measure word))", "鬲 ((surname)/earthen pot/iron caldron)"], "mng": ["hiccup, belch"], "pyn": ["gé"], "exm": [{"cur": "打嗝", "trd": null, "mng": "to hiccup, to belch, to burp", "pyn": "dǎ gé"}, {"cur": "打嗝儿", "trd": "打嗝兒", "mng": "erhua variant of 打嗝[da3 ge2]", "pyn": "dǎ gé r"}, {"cur": "饱嗝儿", "trd": "飽嗝兒", "mng": "to belch (on a full stomach)", "pyn": "bǎo gé r"}, {"cur": "嗝儿屁", "trd": "嗝兒屁", "mng": "(dialect) to die, to give up the ghost", "pyn": "gé r pì"}], "cur": "嗝"}