{"hnz": "圜", "trd": null, "isTrd": false, "cmp": ["囗 (enclosure)", "目 (eye/item/section/list/catalogue/table of contents/order (taxonomy)/goal/name/title)", "睘 (Unknown)", "袁* (Unknown)"], "mng": ["circle, encircle", "circle, round"], "pyn": ["huán", "yuán"], "exm": [{"cur": "转圜", "trd": "轉圜", "mng": "to save or redeem (a situation), to mediate, to intercede", "pyn": "zhuǎn huán"}, {"cur": "转圜余地", "trd": "轉圜餘地", "mng": "to have room to save a situation, margin for error (idiom)", "pyn": "zhuǎn huán yú dì"}], "cur": "圜"}