{"hnz": "坻", "trd": null, "isTrd": false, "cmp": ["土 (earth/dust)", "氏 (clan name/maiden name)", "氐 (name of an ancient tribe, foundation/on the whole)", "丶 (dot)"], "mng": ["islet, rock in river", "place name"], "pyn": ["dǐ", "chí"], "exm": [{"cur": "坻", "trd": null, "mng": "place name", "pyn": "dǐ"}, {"cur": "坻", "trd": null, "mng": "islet, rock in river", "pyn": "chí"}, {"cur": "宝坻", "trd": "寶坻", "mng": "Baodi rural district in Tianjin 天津[Tian1 jin1]", "pyn": "Bǎo dǐ"}, {"cur": "宝坻区", "trd": "寶坻區", "mng": "Baodi rural district in Tianjin 天津[Tian1 jin1]", "pyn": "Bǎo dǐ qū"}], "cur": "坻"}