{"hnz": "壮", "trd": "壯", "isTrd": false, "cmp": ["冫 (ice)", "丬 (half tree trunk)", "丨 (line)", "士 (scholar/warrior/knight)"], "mng": ["to strengthen, strong, robust", "Zhuang ethnic group of Guangxi, the PRC's second most numerous ethnic group, Zhuang: Bouxcuengh"], "pyn": ["zhuàng"], "exm": [{"cur": "壮年", "trd": "壯年", "mng": "lit. robust years, prime of life, summer, able-bodied (fit for military service), mature (talent, garden etc)", "pyn": "zhuàng nián"}, {"cur": "壮族", "trd": "壯族", "mng": "Zhuang ethnic group of Guangxi, the PRC's second most numerous ethnic group, Zhuang: Bouxcuengh", "pyn": "Zhuàng zú"}, {"cur": "壮丽", "trd": "壯麗", "mng": "magnificence, magnificent, majestic, glorious", "pyn": "zhuàng lì"}, {"cur": "健壮", "trd": "健壯", "mng": "robust, healthy, sturdy", "pyn": "jiàn zhuàng"}, {"cur": "壮观", "trd": "壯觀", "mng": "spectacular, magnificent sight", "pyn": "zhuàng guān"}, {"cur": "壮大", "trd": "壯大", "mng": "to expand, to strengthen", "pyn": "zhuàng dà"}, {"cur": "壮举", "trd": "壯舉", "mng": "magnificent feat, impressive feat, heroic undertaking, heroic attempt", "pyn": "zhuàng jǔ"}, {"cur": "雄壮", "trd": "雄壯", "mng": "majestic, awesome, full of power and grandeur", "pyn": "xióng zhuàng"}, {"cur": "壮美", "trd": "壯美", "mng": "magnificent", "pyn": "zhuàng měi"}, {"cur": "悲壮", "trd": "悲壯", "mng": "solemn and stirring, moving and tragic", "pyn": "bēi zhuàng"}], "cur": "壮"}