{"hnz": "娟", "trd": null, "isTrd": false, "cmp": ["女 (female/woman)", "口 (mouth/(a measure word))", "肙 (Unknown)", "月 (moon/month)"], "mng": ["beautiful, graceful"], "pyn": ["juān"], "exm": [{"cur": "娟", "trd": null, "mng": "beautiful, graceful", "pyn": "juān"}, {"cur": "婵娟", "trd": "嬋娟", "mng": "a beautiful woman, graceful and elegant posture, moon", "pyn": "chán juān"}, {"cur": "娟秀", "trd": null, "mng": "beautiful, graceful", "pyn": "juān xiù"}, {"cur": "郑幸娟", "trd": "鄭幸娟", "mng": "Zheng Xingjuan (1989-), Chinese athlete, lady high jumper", "pyn": "Zhèng Xìng juān"}], "cur": "娟"}