{"hnz": "孙", "trd": "孫", "isTrd": false, "cmp": ["子 (11 p.m.-1 a.m./1st earthly branch/child/midnight/son/child/seed/egg/small thing, (noun suff.))", "小 (small/tiny/few/young)"], "mng": ["surname Sun", "grandson, descendant"], "pyn": ["sūn"], "exm": [{"cur": "长孙", "trd": "長孫", "mng": "eldest grandson, the eldest son of one's eldest son", "pyn": "zhǎng sūn"}, {"cur": "长孙", "trd": "長孫", "mng": "two-character surname Zhangsun", "pyn": "Zhǎng sūn"}, {"cur": "子孙", "trd": "子孫", "mng": "offspring, posterity", "pyn": "zǐ sūn"}, {"cur": "外孙女", "trd": "外孫女", "mng": "daughter's daughter, granddaughter", "pyn": "wài sūn nǚ"}, {"cur": "外孙", "trd": "外孫", "mng": "daughter's son, grandson, descendant via the female line", "pyn": "wài sūn"}, {"cur": "孙权", "trd": "孫權", "mng": "Sun Quan (reigned 222-252), southern warlord and king of state of Wu 吳|吴 in the Three Kingdoms period", "pyn": "Sūn Quán"}, {"cur": "孙子", "trd": "孫子", "mng": "grandson, son's son", "pyn": "sūn zi"}, {"cur": "孙子", "trd": "孫子", "mng": "Sun Tzu, also known as Sun Wu 孫武|孙武[Sun1 Wu3] (c. 500 BC, dates of birth and death uncertain), general, strategist and philosopher of the Spring and Autumn Period (700-475 BC), believed to be the author of the “Art of War” 孫子兵法|孙子兵法[Sun1 zi3 Bing1 fa3], one of the Seven Military Classics of ancient China 武經七書|武经七书[Wu3 jing1 Qi1 shu1]", "pyn": "Sūn zǐ"}, {"cur": "孙女", "trd": "孫女", "mng": "son's daughter, granddaughter", "pyn": "sūn nǚ"}, {"cur": "孙悟空", "trd": "孫悟空", "mng": "Sun Wukong, the Monkey King, character with supernatural powers in the novel Journey to the West 西遊記|西游记[Xi1 you2 Ji4], Son Goku, the main character in Dragon Ball 七龍珠|七龙珠[Qi1 long2 zhu1]", "pyn": "Sūn Wù kōng"}], "cur": "孙"}