{"hnz": "宗", "trd": null, "isTrd": false, "cmp": ["宀 (roof)", "二 (two/2)", "示 (to show/reveal)", "小 (small/tiny/few/young)"], "mng": ["school, sect, purpose, model, ancestor, clan, to take as one's model (in academic or artistic work), classifier for batches, items, cases (medical or legal), reservoirs", "surname Zong"], "pyn": ["zōng"], "exm": [{"cur": "宗", "trd": null, "mng": "school, sect, purpose, model, ancestor, clan, to take as one's model (in academic or artistic work), classifier for batches, items, cases (medical or legal), reservoirs", "pyn": "zōng"}, {"cur": "宗", "trd": null, "mng": "surname Zong", "pyn": "Zōng"}, {"cur": "宗教", "trd": null, "mng": "religion", "pyn": "zōng jiào"}, {"cur": "宗旨", "trd": null, "mng": "objective, aim, goal", "pyn": "zōng zhǐ"}, {"cur": "宗派", "trd": null, "mng": "sect", "pyn": "zōng pài"}, {"cur": "禅宗", "trd": "禪宗", "mng": "Zen Buddhism", "pyn": "chán zōng"}, {"cur": "唐太宗", "trd": null, "mng": "Emperor Taizong of Tang, reign name of second Tang emperor Li Shimin 李世民[Li3 Shi4 min2] (599-649), reigned 626-649", "pyn": "Táng Tài zōng"}, {"cur": "世宗", "trd": null, "mng": "Sejong the Great or Sejong Daewang (1397-1450), reigned 1418-1450 as fourth king of Joseon or Chosun dynasty, in whose reign the hangeul alphabet was invented", "pyn": "Shì zōng"}, {"cur": "密宗", "trd": null, "mng": "tantra", "pyn": "mì zōng"}, {"cur": "祖宗", "trd": null, "mng": "ancestor, forebear", "pyn": "zǔ zōng"}, {"cur": "宗族", "trd": null, "mng": "clan, clansman", "pyn": "zōng zú"}, {"cur": "正宗", "trd": null, "mng": "orthodox school, fig. traditional, old school, authentic, genuine", "pyn": "zhèng zōng"}, {"cur": "宗师", "trd": "宗師", "mng": "great scholar respected for learning and integrity", "pyn": "zōng shī"}, {"cur": "大宗", "trd": null, "mng": "large amount, staple, influential family of long standing", "pyn": "dà zōng"}, {"cur": "传宗接代", "trd": "傳宗接代", "mng": "to carry on one's ancestral line", "pyn": "chuán zōng jiē dài"}, {"cur": "高宗", "trd": null, "mng": "Gaozong Emperor, Temple name of the tenth Song Emperor Zhao Gou 趙構|赵构[Zhào Gòu] (1107-1187 CE), reigned (1127-1162 CE)", "pyn": "Gāo Zōng"}, {"cur": "太宗", "trd": null, "mng": "posthumous name given to second emperor of a dynasty, King Taejong of Joseon Korea (1367-1422), reigned 1400-1418", "pyn": "Tài zōng"}, {"cur": "宗教学", "trd": "宗教學", "mng": "religious studies", "pyn": "zōng jiào xué"}, {"cur": "唐玄宗", "trd": null, "mng": "Tang Emperor Xuanzong (685-762), also known as Emperor Ming of Tang 唐明皇[Tang2 Ming2 huang2], reign name of seventh Tang emperor 李隆基[Li3 Long1 ji1], reigned 712-756", "pyn": "Táng Xuán zōng"}, {"cur": "天台宗", "trd": null, "mng": "Tiantai school of Buddhism", "pyn": "Tiān tái zōng"}], "cur": "宗"}