{"hnz": "宜", "trd": null, "isTrd": false, "cmp": ["宀 (roof)", "且 (further/moreover)"], "mng": ["proper, should, suitable, appropriate", "surname Yi"], "pyn": ["yí"], "exm": [{"cur": "便宜", "trd": null, "mng": "convenient", "pyn": "biàn yí"}, {"cur": "便宜", "trd": null, "mng": "cheap, inexpensive, small advantages, to let sb off lightly", "pyn": "pián yi"}, {"cur": "因地制宜", "trd": null, "mng": "(idiom) to use methods in line with local circumstances", "pyn": "yīn dì zhì yí"}, {"cur": "宜人", "trd": null, "mng": "nice, pleasant, charming, hospitable to people", "pyn": "yí rén"}, {"cur": "事宜", "trd": null, "mng": "matters, arrangements", "pyn": "shì yí"}, {"cur": "不宜", "trd": null, "mng": "not suitable, inadvisable, inappropriate", "pyn": "bù yí"}, {"cur": "适宜", "trd": "適宜", "mng": "suitable, appropriate", "pyn": "shì yí"}, {"cur": "相宜", "trd": null, "mng": "to be suitable or appropriate", "pyn": "xiāng yí"}, {"cur": "宜兴", "trd": "宜興", "mng": "Yixing county level city in Wuxi 無錫|无锡[Wu2 xi1], Jiangsu", "pyn": "Yí xīng"}, {"cur": "宜宾", "trd": "宜賓", "mng": "Yibin prefecture level city in Sichuan", "pyn": "Yí bīn"}], "cur": "宜"}