{"hnz": "恃", "trd": null, "isTrd": false, "cmp": ["忄 (heart)", "土 (earth/dust)", "寺 (Buddhist temple)", "寸 (a unit of length/inch/thumb)"], "mng": ["to rely on, mother (formal)"], "pyn": ["shì"], "exm": [{"cur": "自恃", "trd": null, "mng": "self esteem, self reliance, over confident, conceited", "pyn": "zì shì"}, {"cur": "有恃无恐", "trd": "有恃無恐", "mng": "secure in the knowledge that one has backing", "pyn": "yǒu shì wú kǒng"}, {"cur": "怙恃", "trd": null, "mng": "to rely on, father and mother (classical)", "pyn": "hù shì"}, {"cur": "恃才傲物", "trd": null, "mng": "to be inordinately proud of one's ability, to be conceited and contemptuous (idiom)", "pyn": "shì cái ào wù"}, {"cur": "仗恃", "trd": null, "mng": "to rely on, to depend on", "pyn": "zhàng shì"}, {"cur": "凭恃", "trd": "憑恃", "mng": "to depend on, to rely on", "pyn": "píng shì"}, {"cur": "失恃", "trd": null, "mng": "to lose sb one relies upon, to lose one's mother", "pyn": "shī shì"}, {"cur": "恃强欺弱", "trd": "恃強欺弱", "mng": "to use one's strength to mistreat people (idiom), to bully", "pyn": "shì qiáng qī ruò"}, {"cur": "可恃", "trd": null, "mng": "reliable", "pyn": "kě shì"}], "cur": "恃"}