{"hnz": "插", "trd": null, "isTrd": false, "cmp": ["扌 (hand)", "丿 (slash)", "千 (thousand, a swing)", "十 (ten/10)", "臿 (Unknown)", "臼 (mortar)"], "mng": ["to insert, stick in, pierce, to take part in, to interfere, to interpose"], "pyn": ["chā"], "exm": [{"cur": "插", "trd": null, "mng": "to insert, stick in, pierce, to take part in, to interfere, to interpose", "pyn": "chā"}, {"cur": "插入", "trd": null, "mng": "to insert, to stick, to thrust", "pyn": "chā rù"}, {"cur": "穿插", "trd": null, "mng": "to insert, to take turns, alternate, to interweave, to interlace, subplot, interlude, episode, (military) to thrust deep into the enemy forces", "pyn": "chuān chā"}, {"cur": "插图", "trd": "插圖", "mng": "illustration", "pyn": "chā tú"}, {"cur": "插件", "trd": null, "mng": "plug-in (software component)", "pyn": "chā jiàn"}, {"cur": "插花", "trd": null, "mng": "flower arranging, ikebana", "pyn": "chā huā"}, {"cur": "插画", "trd": "插畫", "mng": "illustration", "pyn": "chā huà"}, {"cur": "插手", "trd": null, "mng": "to get involved in, to meddle, interference", "pyn": "chā shǒu"}, {"cur": "插队", "trd": "插隊", "mng": "to cut in line, to jump a queue, to live on a rural community (during the Cultural Revolution)", "pyn": "chā duì"}, {"cur": "插头", "trd": "插頭", "mng": "plug", "pyn": "chā tóu"}, {"cur": "插曲", "trd": null, "mng": "music played during a movie, play etc, incidental music, music played in a theatrical interlude, (fig.) incident, episode", "pyn": "chā qǔ"}, {"cur": "插座", "trd": null, "mng": "socket, outlet", "pyn": "chā zuò"}, {"cur": "插值", "trd": null, "mng": "interpolation", "pyn": "chā zhí"}, {"cur": "插口", "trd": null, "mng": "socket (for an electric plug), to interrupt (sb speaking), to butt in", "pyn": "chā kǒu"}, {"cur": "不插电", "trd": "不插電", "mng": "unplugged (of rock musicians performing on acoustic instruments)", "pyn": "bù chā diàn"}, {"cur": "热插拔", "trd": "熱插拔", "mng": "hot swapping", "pyn": "rè chā bá"}, {"cur": "插秧", "trd": null, "mng": "transplant rice seedlings", "pyn": "chā yāng"}, {"cur": "即插即用", "trd": null, "mng": "plug-and-play", "pyn": "jí chā jí yòng"}, {"cur": "插进", "trd": "插進", "mng": "to insert, to stick in, to plug in (an electronic device)", "pyn": "chā jìn"}, {"cur": "插上", "trd": null, "mng": "to plug into, to insert, to stick in", "pyn": "chā shang"}], "cur": "插"}