{"hnz": "榫", "trd": null, "isTrd": false, "cmp": ["木 (tree/wood)", "隹 (short-tailed bird)", "隼 (Unknown)", "十 (ten/10)"], "mng": ["mortise and tenon (slot and tab forming a carpenter's joint)"], "pyn": ["sǔn"], "exm": [{"cur": "榫", "trd": null, "mng": "mortise and tenon (slot and tab forming a carpenter's joint)", "pyn": "sǔn"}, {"cur": "榫头", "trd": "榫頭", "mng": "tenon (wooden projection to fit into a mortise)", "pyn": "sǔn tou"}, {"cur": "榫眼", "trd": null, "mng": "mortise (slot cut into wood to receive a tenon)", "pyn": "sǔn yǎn"}, {"cur": "卯榫", "trd": null, "mng": "mortise and tenon (slot and tab forming a carpenter's joint)", "pyn": "mǎo sǔn"}, {"cur": "榫凿", "trd": "榫鑿", "mng": "mortise chisel", "pyn": "sǔn záo"}, {"cur": "榫销", "trd": "榫銷", "mng": "dowel, carpenter's pin", "pyn": "sǔn xiāo"}, {"cur": "卡榫", "trd": null, "mng": "clip, latch (on a clip-into-place component)", "pyn": "kǎ sǔn"}], "cur": "榫"}