{"hnz": "浜", "trd": null, "isTrd": false, "cmp": ["氵 (water)", "丘 (Confucius/given name/mound, earthenware, earthenware vessel)", "兵 (soldiers/a force/an army/weapons/arms/military/warlike)", "八 (eight/8)"], "mng": ["stream, creek", "Japanese variant of 濱|滨[bin1], used in Japanese place names such as Yokohama 橫浜|横浜[Heng2 bin1] with phonetic value hama"], "pyn": ["bāng", "bīn"], "exm": [{"cur": "沙家浜", "trd": null, "mng": "\"Sha Family's Creek\", a Beijing opera classified as model theater 樣板戲|样板戏[yang4 ban3 xi4]", "pyn": "Shā jiā bāng"}, {"cur": "横浜", "trd": "橫浜", "mng": "Japanese spelling of Yokohama (Chinese spelling 橫濱|横滨[Héng bīn])", "pyn": "Héng bīn"}, {"cur": "洋泾浜英语", "trd": "洋涇浜英語", "mng": "pidgin English", "pyn": "Yáng jīng bāng Yīng yǔ"}], "cur": "浜"}