{"hnz": "涣", "trd": "渙", "isTrd": false, "cmp": ["氵 (water)", "⺈ (Unknown)", "奂 ((surname)/excellent)", "冂 (down box)", "央 (beg/center)", "大 (big/huge/large/major/great/wide/deep/oldest/eldest, doctor)"], "mng": ["to dissipate, to dissolve"], "pyn": ["huàn"], "exm": [{"cur": "涣", "trd": "渙", "mng": "to dissipate, to dissolve", "pyn": "huàn"}, {"cur": "涣散", "trd": "渙散", "mng": "to slacken, lax, slack, disorganized", "pyn": "huàn sàn"}, {"cur": "涣然", "trd": "渙然", "mng": "to dissipate, to vanish", "pyn": "huàn rán"}, {"cur": "涣然冰释", "trd": "渙然冰釋", "mng": "to melt away (idiom), to clear up, to dissipate", "pyn": "huàn rán bīng shì"}], "cur": "涣"}