{"hnz": "灌", "trd": null, "isTrd": false, "cmp": ["氵 (water)", "艹 (grass)", "雚 (Unknown)", "口 (mouth/(a measure word))", "𨾴 (Unknown)", "隹 (short-tailed bird)"], "mng": ["to irrigate, to pour, to install (software), to record (music)"], "pyn": ["guàn"], "exm": [{"cur": "灌", "trd": null, "mng": "to irrigate, to pour, to install (software), to record (music)", "pyn": "guàn"}, {"cur": "灌木", "trd": null, "mng": "bush, shrub", "pyn": "guàn mù"}, {"cur": "灌注", "trd": null, "mng": "to pour into, perfusion (med.), to concentrate one's attention on, to teach, to inculcate, to instill", "pyn": "guàn zhù"}, {"cur": "浇灌", "trd": "澆灌", "mng": "to water, to irrigate", "pyn": "jiāo guàn"}, {"cur": "灌输", "trd": "灌輸", "mng": "to imbue with, to inculcate, to instill into, to teach, to impart, to channel water to another place", "pyn": "guàn shū"}, {"cur": "灌水", "trd": null, "mng": "lit. to irrigate, to artificially increase weight, to cook the books, to leave a tasteless message", "pyn": "guàn shuǐ"}, {"cur": "灌溉", "trd": null, "mng": "to irrigate", "pyn": "guàn gài"}, {"cur": "灌区", "trd": "灌區", "mng": "area under irrigation", "pyn": "guàn qū"}, {"cur": "灌肠", "trd": "灌腸", "mng": "enema, to give an enema", "pyn": "guàn cháng"}, {"cur": "灌肠", "trd": "灌腸", "mng": "sausage with a starchy filling", "pyn": "guàn chang"}, {"cur": "灌浆", "trd": "灌漿", "mng": "grouting, (of grain) to be in the milk, to form a vesicle (medicine)", "pyn": "guàn jiāng"}, {"cur": "灌篮", "trd": "灌籃", "mng": "slam dunk", "pyn": "guàn lán"}, {"cur": "滴灌", "trd": null, "mng": "drip irrigation, to irrigate by drip feed", "pyn": "dī guàn"}, {"cur": "灌醉", "trd": null, "mng": "to fuddle, to befuddle, to inebriate, to get someone drunk", "pyn": "guàn zuì"}, {"cur": "灌云", "trd": "灌雲", "mng": "Guanyun county in Lianyungang 連雲港|连云港[Lian2 yun2 gang3], Jiangsu", "pyn": "Guàn yún"}, {"cur": "灌木丛", "trd": "灌木叢", "mng": "shrub, shrubbery", "pyn": "guàn mù cóng"}, {"cur": "灌南", "trd": null, "mng": "Guannan county in Lianyungang 連雲港|连云港[Lian2 yun2 gang3], Jiangsu", "pyn": "Guàn nán"}, {"cur": "灌阳", "trd": "灌陽", "mng": "Guanyang county in Guilin 桂林[Gui4 lin2], Guangxi", "pyn": "Guàn yáng"}, {"cur": "灌丛", "trd": "灌叢", "mng": "scrub, shrubland, undergrowth", "pyn": "guàn cóng"}, {"cur": "醍醐灌顶", "trd": "醍醐灌頂", "mng": "lit. to anoint your head with the purest cream (idiom); fig. to enlighten people with perfect wisdom, flawless Buddhist teaching", "pyn": "tí hú guàn dǐng"}], "cur": "灌"}