{"hnz": "瓦", "trd": null, "isTrd": false, "cmp": [], "mng": ["roof tile, abbr. for 瓦特[wa3 te4], watt (loan)"], "pyn": ["wǎ"], "exm": [{"cur": "瓦", "trd": null, "mng": "roof tile, abbr. for 瓦特[wa3 te4], watt (loan)", "pyn": "wǎ"}, {"cur": "日内瓦", "trd": "日內瓦", "mng": "Geneva, Switzerland", "pyn": "Rì nèi wǎ"}, {"cur": "瓦解", "trd": null, "mng": "to collapse, to disintegrate, to crumble", "pyn": "wǎ jiě"}, {"cur": "瓦特", "trd": null, "mng": "watt (loanword)", "pyn": "wǎ tè"}, {"cur": "科特迪瓦", "trd": null, "mng": "Côte d'Ivoire or Ivory Coast in West Africa", "pyn": "Kē tè dí wǎ"}, {"cur": "瓦斯", "trd": null, "mng": "gas (loanword)", "pyn": "wǎ sī"}, {"cur": "千瓦", "trd": null, "mng": "kilowatt (unit of electric power)", "pyn": "qiān wǎ"}, {"cur": "萨尔瓦多", "trd": "薩爾瓦多", "mng": "El Salvador", "pyn": "Sà ěr wǎ duō"}, {"cur": "摩尔多瓦", "trd": "摩爾多瓦", "mng": "Moldova, Republic of Moldova, former Soviet republic on the border with Romania", "pyn": "Mó ěr duō wǎ"}, {"cur": "砖瓦", "trd": "磚瓦", "mng": "tiles and bricks", "pyn": "zhuān wǎ"}, {"cur": "瓦房店", "trd": null, "mng": "Wangfangdian county level city in Dalian 大連|大连[Da4 lian2], Liaoning", "pyn": "Wǎ fáng diàn"}, {"cur": "兆瓦", "trd": null, "mng": "megawatt", "pyn": "zhào wǎ"}, {"cur": "施瓦辛格", "trd": null, "mng": "Arnold Schwarzenegger (1947-), US actor and politician, governor of California 2003-2011", "pyn": "Shī wǎ xīn gé"}, {"cur": "博茨瓦纳", "trd": "博茨瓦納", "mng": "Botswana", "pyn": "Bó cí wǎ nà"}, {"cur": "瓦利", "trd": null, "mng": "Váli (son of Odin)", "pyn": "Wǎ lì"}, {"cur": "瓦片", "trd": null, "mng": "tile", "pyn": "wǎ piàn"}, {"cur": "瓦努阿图", "trd": "瓦努阿圖", "mng": "Vanuatu in south pacific (formerly New Hebrides)", "pyn": "Wǎ nǔ ā tú"}, {"cur": "斯瓦希里", "trd": "斯瓦希裡", "mng": "Swahili", "pyn": "Sī wǎ xī lǐ"}, {"cur": "哈瓦那", "trd": null, "mng": "Havana, capital of Cuba", "pyn": "Hā wǎ nà"}, {"cur": "瓦砾", "trd": "瓦礫", "mng": "rubble, debris", "pyn": "wǎ lì"}], "cur": "瓦"}