{"hnz": "矶", "trd": "磯", "isTrd": false, "cmp": ["石 (10 pecks, rock/stone)", "几 (small table, almost, a few/how many, how much/how many/several/a few)"], "mng": ["breakwater, jetty"], "pyn": ["jī"], "exm": [{"cur": "洛杉矶", "trd": "洛杉磯", "mng": "Los Angeles, California", "pyn": "Luò shān jī"}, {"cur": "洛杉矶时报", "trd": "洛杉磯時報", "mng": "Los Angeles Times", "pyn": "luò shān jī shí bào"}, {"cur": "加利福尼亚大学洛杉矶分校", "trd": "加利福尼亞大學洛杉磯分校", "mng": "UCLA", "pyn": "Jiā lì fú ní yà Dà xué Luò shān jī fēn xiào"}, {"cur": "洛矶山脉", "trd": "洛磯山脈", "mng": "the Rocky Mountains", "pyn": "luò jī shān mài"}, {"cur": "洛矶山", "trd": "洛磯山", "mng": "Rocky Mountains", "pyn": "Luò jī shān"}, {"cur": "矶鹬", "trd": "磯鷸", "mng": "(bird species of China) common sandpiper (Actitis hypoleucos)", "pyn": "jī yù"}, {"cur": "白背矶鸫", "trd": "白背磯鶇", "mng": "(bird species of China) common rock thrush (Monticola saxatilis)", "pyn": "bái bèi jī dōng"}, {"cur": "白喉矶鸫", "trd": "白喉磯鶇", "mng": "(bird species of China) white-throated rock thrush (Monticola gularis)", "pyn": "bái hóu jī dōng"}, {"cur": "洛矶山脉", "trd": "洛磯山脈", "mng": "Rocky Mountains", "pyn": "Luò jī Shān mài"}, {"cur": "洛矶山", "trd": "洛磯山", "mng": "Rocky Mountains", "pyn": "Luò jī Shān"}], "cur": "矶"}