{"hnz": "砒", "trd": null, "isTrd": false, "cmp": ["石 (10 pecks, rock/stone)", "匕 (an ancient type of spoon, dagger/ladle)", "比 ((particle used for comparison and \"-er than\")/to compare/to contrast/to gesture (with hands)/ratio, associate with/be near)", "匕 (an ancient type of spoon, dagger/ladle)"], "mng": ["arsenic"], "pyn": ["pī"], "exm": [{"cur": "白砒", "trd": null, "mng": "white arsenic, arsenic trioxide", "pyn": "bái pī"}, {"cur": "砒霜", "trd": null, "mng": "white arsenic, arsenic trioxide As2O3", "pyn": "pī shuāng"}], "cur": "砒"}