{"hnz": "穢", "trd": "穢", "isTrd": true, "cmp": ["丿 (slash)", "禾 (cereal/grain)", "木 (tree/wood)", "止 (to stop/toe)", "歲 (Unknown)", "戊少 (Unknown)"], "mng": ["dirt, filth"], "pyn": ["huì"], "exm": [{"cur": "秽", "trd": "穢", "mng": "dirt, filth", "pyn": "huì"}, {"cur": "污秽", "trd": "污穢", "mng": "nasty, sordid, filthy", "pyn": "wū huì"}, {"cur": "淫秽", "trd": "淫穢", "mng": "obscene, coarse", "pyn": "yín huì"}, {"cur": "秽语", "trd": "穢語", "mng": "obscene language", "pyn": "huì yǔ"}, {"cur": "污言秽语", "trd": "污言穢語", "mng": "filthy speech, obscenities", "pyn": "wū yán huì yǔ"}, {"cur": "自惭形秽", "trd": "自慚形穢", "mng": "to feel ashamed of one's inferiority (idiom), to feel inferior", "pyn": "zì cán xíng huì"}, {"cur": "芜秽", "trd": "蕪穢", "mng": "to be overgrown with weeds", "pyn": "wú huì"}, {"cur": "淫词秽语", "trd": "淫詞穢語", "mng": "obscene words, dirty talk", "pyn": "yín cí huì yǔ"}], "cur": "秽"}