{"hnz": "章", "trd": null, "isTrd": false, "cmp": ["立 (set up/to stand)", "日 (Japan/day/sun/date/day of the month)", "早 (early/morning)", "十 (ten/10)"], "mng": ["chapter, section, clause, movement (of symphony), seal, badge, regulation, order", "surname Zhang"], "pyn": ["zhāng"], "exm": [{"cur": "文章", "trd": null, "mng": "article, essay, literary works, writings, hidden meaning", "pyn": "wén zhāng"}, {"cur": "规章", "trd": "規章", "mng": "rule, regulation", "pyn": "guī zhāng"}, {"cur": "党章", "trd": "黨章", "mng": "party constitution", "pyn": "dǎng zhāng"}, {"cur": "顺理成章", "trd": "順理成章", "mng": "logical, only to be expected, rational and clearly structured (of text)", "pyn": "shùn lǐ chéng zhāng"}, {"cur": "篇章", "trd": null, "mng": "writing, sections and chapters", "pyn": "piān zhāng"}, {"cur": "章程", "trd": null, "mng": "rules, regulations, constitution, statute, articles of association (of company), articles of incorporation, charter (of a corporation), by-laws", "pyn": "zhāng chéng"}, {"cur": "报章", "trd": "報章", "mng": "newspapers", "pyn": "bào zhāng"}, {"cur": "宪章", "trd": "憲章", "mng": "charter", "pyn": "xiàn zhāng"}, {"cur": "印章", "trd": null, "mng": "seal, signet, chop, stamp", "pyn": "yìn zhāng"}, {"cur": "公章", "trd": null, "mng": "official seal", "pyn": "gōng zhāng"}], "cur": "章"}