{"hnz": "簽", "trd": "簽", "isTrd": true, "cmp": ["亇 (Unknown)", "竹 (bamboo)", "亇 (Unknown)", "人 (man/person/people)", "亼 (Unknown)", "一 (one/1/single/a(n))", "僉 (Unknown)", "兄兄 (Unknown)"], "mng": ["to sign one's name, visa, variant of 籤|签[qian1]"], "pyn": ["qiān"], "exm": [{"cur": "签", "trd": "簽", "mng": "to sign one's name, visa, variant of 籤|签[qian1]", "pyn": "qiān"}, {"cur": "书签", "trd": "書簽", "mng": "bookmark, also written 書籤|书签[shū qiān]", "pyn": "shū qiān"}, {"cur": "签名", "trd": "簽名", "mng": "to sign (one's name with a pen etc), to autograph, signature", "pyn": "qiān míng"}, {"cur": "签订", "trd": "簽訂", "mng": "to agree to and sign (a treaty etc)", "pyn": "qiān dìng"}, {"cur": "抽签", "trd": "抽簽", "mng": "variant of 抽籤|抽签[chōu qiān]", "pyn": "chōu qiān"}, {"cur": "签发", "trd": "簽發", "mng": "to issue (a document), to sign and issue officially", "pyn": "qiān fā"}, {"cur": "签字", "trd": "簽字", "mng": "to sign (one's name), signature", "pyn": "qiān zì"}, {"cur": "棉签", "trd": "棉簽", "mng": "variant of 棉籤|棉签[mian2 qian1], cotton swab", "pyn": "mián qiān"}, {"cur": "签约", "trd": "簽約", "mng": "to sign a contract or agreement", "pyn": "qiān yuē"}, {"cur": "签署", "trd": "簽署", "mng": "to sign (an agreement)", "pyn": "qiān shǔ"}, {"cur": "牙签", "trd": "牙簽", "mng": "variant of 牙籤|牙签[yá qiān], toothpick", "pyn": "yá qiān"}, {"cur": "续签", "trd": "續簽", "mng": "to renew a contract, contract extension", "pyn": "xù qiān"}, {"cur": "签到", "trd": "簽到", "mng": "to register, to sign in", "pyn": "qiān dào"}, {"cur": "签收", "trd": "簽收", "mng": "to sign for the acceptance of sth (e.g. a delivery etc)", "pyn": "qiān shōu"}, {"cur": "签证", "trd": "簽證", "mng": "visa, certificate, to certify", "pyn": "qiān zhèng"}, {"cur": "中签", "trd": "中簽", "mng": "to win a ballot, to draw a lucky number", "pyn": "zhòng qiān"}, {"cur": "签定", "trd": "簽定", "mng": "to sign (a contract, treaty etc)", "pyn": "qiān dìng"}, {"cur": "签出", "trd": "簽出", "mng": "to log off", "pyn": "qiān chū"}, {"cur": "签章", "trd": "簽章", "mng": "signature", "pyn": "qiān zhāng"}, {"cur": "便签", "trd": "便簽", "mng": "note, memo", "pyn": "biàn qiān"}], "cur": "签"}