{"hnz": "裡", "trd": "裡", "isTrd": true, "cmp": ["衤 (clothes)", "田 ((surname)/field/farm)", "里 (inside/internal/interior, village/within/inside, Chinese mile/neighborhood/li, a Chinese unit of length = one-half kilometer/hometown)", "土 (earth/dust)"], "mng": ["lining, interior, inside, internal, also written 裏|里[li3]"], "pyn": ["lǐ"], "exm": [{"cur": "里", "trd": "裡", "mng": "lining, interior, inside, internal, also written 裏|里[li3]", "pyn": "lǐ"}, {"cur": "这里", "trd": "這裡", "mng": "here", "pyn": "zhè lǐ"}, {"cur": "哪里", "trd": "哪裡", "mng": "where?, somewhere, anywhere, wherever, nowhere (negative answer to question), humble expression denying compliment", "pyn": "nǎ lǐ"}, {"cur": "里面", "trd": "裡面", "mng": "inside, interior", "pyn": "lǐ miàn"}, {"cur": "手里", "trd": "手裡", "mng": "in hand, (a situation is) in sb's hands", "pyn": "shǒu lǐ"}, {"cur": "那里", "trd": "那裡", "mng": "there, that place", "pyn": "nà li"}, {"cur": "心里", "trd": "心裡", "mng": "chest, heart, mind", "pyn": "xīn li"}, {"cur": "家里", "trd": "家裡", "mng": "home", "pyn": "jiā lǐ"}, {"cur": "字里行间", "trd": "字裡行間", "mng": "between the words and the lines (idiom); implied meaning, connotations", "pyn": "zì lǐ háng jiān"}, {"cur": "海里", "trd": "海裡", "mng": "marine", "pyn": "hǎi lǐ"}, {"cur": "索马里", "trd": "索馬裡", "mng": "variant of 索馬里|索马里[Suo3 ma3 li3], Somalia", "pyn": "Suǒ mǎ lǐ"}, {"cur": "骨子里", "trd": "骨子裡", "mng": "what sb feels (or knows etc) in his bones (derog.), private understanding between individuals (derog.)", "pyn": "gǔ zi lǐ"}, {"cur": "千里眼", "trd": "千裡眼", "mng": "clairvoyance", "pyn": "qiān lǐ yǎn"}, {"cur": "毛里求斯", "trd": "毛裡求斯", "mng": "Mauritius", "pyn": "Máo lǐ qiú sī"}, {"cur": "里加", "trd": "裡加", "mng": "Riga, capital of Latvia", "pyn": "Lǐ jiā"}, {"cur": "里昂", "trd": "裡昂", "mng": "Lyon, French city on the Rhône", "pyn": "Lǐ áng"}, {"cur": "夜里", "trd": "夜裡", "mng": "during the night, at night, nighttime", "pyn": "yè lǐ"}, {"cur": "里带", "trd": "裡帶", "mng": "inner tube (of tire)", "pyn": "lǐ dài"}, {"cur": "满洲里", "trd": "滿洲裡", "mng": "Manzhouli county level city, Mongolian Manzhuur xot, in Hulunbuir 呼倫貝爾|呼伦贝尔[Hū lún bèi ěr], Inner Mongolia", "pyn": "Mǎn zhōu lǐ"}, {"cur": "暗地里", "trd": "暗地裡", "mng": "secretly, inwardly, on the sly", "pyn": "àn dì li"}], "cur": "里"}