{"hnz": "贡", "trd": "貢", "isTrd": false, "cmp": ["工 (work/worker/skill/profession/trade/craft/labor)", "冂 (down box)", "贝 (cowries/shell/valuables/shellfish)", "人 (man/person/people)"], "mng": ["to offer tribute, tribute, gifts", "surname Gong"], "pyn": ["gòng"], "exm": [{"cur": "贡", "trd": "貢", "mng": "to offer tribute, tribute, gifts", "pyn": "gòng"}, {"cur": "贡", "trd": "貢", "mng": "surname Gong", "pyn": "Gòng"}, {"cur": "贡献者", "trd": "貢獻者", "mng": "contributor, benefactor", "pyn": "gòng xiàn zhě"}, {"cur": "贡献", "trd": "貢獻", "mng": "to contribute, to dedicate, to devote, contribution", "pyn": "gòng xiàn"}, {"cur": "自贡", "trd": "自貢", "mng": "Zigong prefecture level city in Sichuan", "pyn": "Zì gòng"}, {"cur": "贡品", "trd": "貢品", "mng": "tribute", "pyn": "gòng pǐn"}, {"cur": "自贡市", "trd": "自貢市", "mng": "Zigong prefecture level city in Sichuan", "pyn": "Zì gòng shì"}, {"cur": "重大贡献", "trd": "重大貢獻", "mng": "important contribution, major role", "pyn": "zhòng dà gòng xiàn"}, {"cur": "西贡", "trd": "西貢", "mng": "Saigon, capital of former South Vietnam, Sai Kung town in New Territories, Hong Kong", "pyn": "Xī gòng"}, {"cur": "呈贡", "trd": "呈貢", "mng": "Chenggong county in Kunming 昆明[Kun1 ming2], Yunnan", "pyn": "Chéng gòng"}, {"cur": "贡嘎", "trd": "貢嘎", "mng": "Gonggar county, Tibetan: Gong dkar rdzong, in Lhokha prefecture 山南地區|山南地区[Shan1 nan2 di4 qu1], Tibet", "pyn": "Gòng gá"}, {"cur": "贡丸", "trd": "貢丸", "mng": "pork ball", "pyn": "gòng wán"}, {"cur": "进贡", "trd": "進貢", "mng": "to offer tribute, to pay tribute that a vassal owes to his suzerain", "pyn": "jìn gòng"}, {"cur": "贡寮", "trd": "貢寮", "mng": "Gongliao or Kungliao township in New Taipei City 新北市[Xin1 bei3 shi4], Taiwan", "pyn": "Gòng liáo"}, {"cur": "贡山", "trd": "貢山", "mng": "Gongshan Derung and Nu autonomous county in Nujiang Lisu autonomous prefecture 怒江傈僳族自治州[Nu4 jiang1 Li4 su4 zu2 zi4 zhi4 zhou1] in northwest Yunnan", "pyn": "Gòng shān"}, {"cur": "贡士", "trd": "貢士", "mng": "(old) candidate who has successfully passed the first grades of the examination system, but not yet the court examination (殿試|殿试[dian4 shi4])", "pyn": "gòng shì"}, {"cur": "章贡", "trd": "章貢", "mng": "Zhanggong district of Ganzhou city 贛州市|赣州市, Jiangxi", "pyn": "Zhāng gòng"}, {"cur": "子贡", "trd": "子貢", "mng": "Zi Gong or Duanmu Ci 端木賜|端木赐[Duan1 mu4 Ci4] (520 BC-), disciple of Confucius", "pyn": "Zǐ Gòng"}, {"cur": "章贡区", "trd": "章貢區", "mng": "Zhanggong district of Ganzhou city 贛州市|赣州市, Jiangxi", "pyn": "Zhāng gòng qū"}, {"cur": "朝贡", "trd": "朝貢", "mng": "to present tribute (to the emperor)", "pyn": "cháo gòng"}], "cur": "贡"}