{"hnz": "贱", "trd": "賤", "isTrd": false, "cmp": ["冂 (down box)", "贝 (cowries/shell/valuables/shellfish)", "人 (man/person/people)", "一 (one/1/single/a(n))", "戋 (narrow/small)", "弋 (to shoot)", "戈 ((surname)/spear)", "丿 (slash)"], "mng": ["inexpensive, lowly"], "pyn": ["jiàn"], "exm": [{"cur": "贱", "trd": "賤", "mng": "inexpensive, lowly", "pyn": "jiàn"}, {"cur": "贵贱", "trd": "貴賤", "mng": "noble and lowly, high versus low social hierarchy of ruler to people, father to son, husband to wife in Confucianism", "pyn": "guì jiàn"}, {"cur": "贱卖", "trd": "賤賣", "mng": "to sell cheaply, sacrifice, low price, discount sale", "pyn": "jiàn mài"}, {"cur": "贫贱", "trd": "貧賤", "mng": "poor and lowly", "pyn": "pín jiàn"}, {"cur": "贱人", "trd": "賤人", "mng": "slut, cheap person", "pyn": "jiàn rén"}, {"cur": "卑贱", "trd": "卑賤", "mng": "lowly, mean and low", "pyn": "bēi jiàn"}, {"cur": "贱民", "trd": "賤民", "mng": "social stratum below the level of ordinary people, untouchable, dalit (India caste)", "pyn": "jiàn mín"}, {"cur": "贫贱不能移", "trd": "貧賤不能移", "mng": "not shaken by poverty, to preserve one's ambitions although destitute", "pyn": "pín jiàn bù néng yí"}, {"cur": "淫贱", "trd": "淫賤", "mng": "morally loose, lewd and low, lascivious and mean, wanton", "pyn": "yín jiàn"}, {"cur": "微贱", "trd": "微賤", "mng": "humble, lowly", "pyn": "wēi jiàn"}, {"cur": "贱骨头", "trd": "賤骨頭", "mng": "miserable wretch, contemptible individual", "pyn": "jiàn gǔ tou"}, {"cur": "贱内", "trd": "賤內", "mng": "my wife (humble)", "pyn": "jiàn nèi"}, {"cur": "大贱卖", "trd": "大賤賣", "mng": "to sell at a big discount", "pyn": "dà jiàn mài"}, {"cur": "贱称", "trd": "賤稱", "mng": "contemptuous term", "pyn": "jiàn chēng"}, {"cur": "亲疏贵贱", "trd": "親疏貴賤", "mng": "close and distant, rich and poor (idiom); everyone, all possible relations", "pyn": "qīn shū guì jiàn"}, {"cur": "贵远贱近", "trd": "貴遠賤近", "mng": "to revere the past and despise the present (idiom)", "pyn": "guì yuǎn jiàn jìn"}, {"cur": "贵古贱今", "trd": "貴古賤今", "mng": "to revere the past and despise the present (idiom)", "pyn": "guì gǔ jiàn jīn"}, {"cur": "泼贱", "trd": "潑賤", "mng": "base, worthless", "pyn": "pō jiàn"}, {"cur": "威尊命贱", "trd": "威尊命賤", "mng": "orders weightier than life", "pyn": "wēi zūn mìng jiàn"}, {"cur": "泼贱人", "trd": "潑賤人", "mng": "slut, tramp (old)", "pyn": "pō jiàn rén"}], "cur": "贱"}