{"hnz": "酉", "trd": null, "isTrd": false, "cmp": [], "mng": ["10th earthly branch: 5-7 p.m., 8th solar month (8th September-7th October), year of the Rooster, ancient Chinese compass point: 270° (west)"], "pyn": ["yǒu"], "exm": [{"cur": "酉", "trd": null, "mng": "10th earthly branch: 5-7 p.m., 8th solar month (8th September-7th October), year of the Rooster, ancient Chinese compass point: 270° (west)", "pyn": "yǒu"}, {"cur": "酉阳", "trd": "酉陽", "mng": "Youyang Tujiazu-Miaozu autonomous county in Sichuan", "pyn": "Yǒu yáng"}, {"cur": "乙酉", "trd": null, "mng": "twenty second year B10 of the 60 year cycle, e.g. 2005 or 2065", "pyn": "yǐ yǒu"}, {"cur": "辛酉", "trd": null, "mng": "fifty eighth year H10 of the 60 year cycle, e.g. 1981 or 2041", "pyn": "xīn yǒu"}, {"cur": "丁酉", "trd": null, "mng": "thirty fourth year D10 of the 60 year cycle, e.g. 1957 or 2017", "pyn": "dīng yǒu"}, {"cur": "癸酉", "trd": null, "mng": "tenth year J10 of the 60 year cycle, e.g. 1993 or 2053", "pyn": "guǐ yǒu"}, {"cur": "己酉", "trd": null, "mng": "forty sixth year F10 of the 60 year cycle, e.g. 1969 or 2029", "pyn": "jǐ yǒu"}, {"cur": "酉阳县", "trd": "酉陽縣", "mng": "Youyang Miao and Tujia autonomous county in Qianjiang suburbs of Chongqing municipality", "pyn": "Yǒu yáng xiàn"}, {"cur": "酉时", "trd": "酉時", "mng": "5-7 pm (in the system of two-hour subdivisions used in former times)", "pyn": "yǒu shí"}, {"cur": "酉鸡", "trd": "酉雞", "mng": "Year 10, year of the Cock (e.g. 2005)", "pyn": "yǒu jī"}, {"cur": "酉阳土家族苗族自治县", "trd": "酉陽土家族苗族自治縣", "mng": "Youyang Miao and Tujia autonomous county in Qianjiang suburbs of Chongqing municipality", "pyn": "Yǒu yáng Tǔ jiā zú Miáo zú zì zhì xiàn"}, {"cur": "酉牌时分", "trd": "酉牌時分", "mng": "5-7 pm", "pyn": "yǒu pái shí fēn"}], "cur": "酉"}