{"hnz": "除", "trd": null, "isTrd": false, "cmp": ["阝 (city)", "人 (man/person/people)", "亼 (Unknown)", "一 (one/1/single/a(n))", "余 (extra/surplus/remaining/after/I/me)", "朩 (Unknown)"], "mng": ["to get rid of, to remove, to exclude, to eliminate, to wipe out, to divide, except, not including"], "pyn": ["chú"], "exm": [{"cur": "除", "trd": null, "mng": "to get rid of, to remove, to exclude, to eliminate, to wipe out, to divide, except, not including", "pyn": "chú"}, {"cur": "除了", "trd": null, "mng": "besides, apart from (... also...), in addition to, except (for)", "pyn": "chú le"}, {"cur": "删除", "trd": "刪除", "mng": "to delete, to cancel", "pyn": "shān chú"}, {"cur": "清除", "trd": null, "mng": "to clear away, to eliminate, to get rid of", "pyn": "qīng chú"}, {"cur": "解除", "trd": null, "mng": "to remove, to sack, to get rid of, to relieve (sb of their duties), to free, to lift (an embargo), to rescind (an agreement)", "pyn": "jiě chú"}, {"cur": "免除", "trd": null, "mng": "to prevent, to avoid, to excuse, to exempt, to relieve, (of a debt) to remit", "pyn": "miǎn chú"}, {"cur": "切除", "trd": null, "mng": "to excise, to cut out (a tumor)", "pyn": "qiē chú"}, {"cur": "排除", "trd": null, "mng": "to eliminate, to remove, to exclude, to rule out", "pyn": "pái chú"}, {"cur": "消除", "trd": null, "mng": "to eliminate, to remove", "pyn": "xiāo chú"}, {"cur": "除去", "trd": null, "mng": "to eliminate, to remove, except for, apart from", "pyn": "chú qù"}, {"cur": "根除", "trd": null, "mng": "to eradicate", "pyn": "gēn chú"}, {"cur": "除草", "trd": null, "mng": "to weed", "pyn": "chú cǎo"}, {"cur": "剔除", "trd": null, "mng": "to reject, to discard, to get rid of", "pyn": "tī chú"}, {"cur": "破除", "trd": null, "mng": "to eliminate, to do away with, to get rid of", "pyn": "pò chú"}, {"cur": "除非", "trd": null, "mng": "only if (..., or otherwise, ...), only when, only in the case that, unless", "pyn": "chú fēi"}, {"cur": "撤除", "trd": null, "mng": "to remove, to dismantle", "pyn": "chè chú"}, {"cur": "除名", "trd": null, "mng": "to strike off (the rolls), to remove from a list, to expunge, to expel", "pyn": "chú míng"}, {"cur": "摘除", "trd": null, "mng": "to excise, to remove an organ", "pyn": "zhāi chú"}, {"cur": "铲除", "trd": "剷除", "mng": "to root out, to eradicate, to sweep away, to abolish", "pyn": "chǎn chú"}, {"cur": "除外", "trd": null, "mng": "to exclude, not including sth (when counting or listing), except for", "pyn": "chú wài"}], "cur": "除"}