{"hnz": "霞", "trd": null, "isTrd": false, "cmp": ["雨 (rain)", "叚 (Unknown)"], "mng": ["red clouds"], "pyn": ["xiá"], "exm": [{"cur": "彩霞", "trd": null, "mng": "clouds tinged with sunset hues", "pyn": "cǎi xiá"}, {"cur": "林青霞", "trd": null, "mng": "Brigitte Lin (1954-), Taiwanese actress", "pyn": "Lín Qīng xiá"}, {"cur": "晚霞", "trd": null, "mng": "sunset glow, sunset clouds, afterglow", "pyn": "wǎn xiá"}, {"cur": "栖霞", "trd": "棲霞", "mng": "Xixia county level city in Yantai 煙台|烟台, Shandong", "pyn": "Xī xiá"}, {"cur": "霞浦", "trd": null, "mng": "Xiapu county in Ningde 寧德|宁德[Ning2 de2], Fujian", "pyn": "Xiá pǔ"}, {"cur": "丹霞", "trd": null, "mng": "Mt Danxia in Shaoguan 韶關|韶关[Sháo guān], Guangdong, Danxia landform, red conglomerate and sandstone", "pyn": "dān xiá"}, {"cur": "丹霞山", "trd": null, "mng": "Mt Danxia in Shaoguan 韶關|韶关[Sháo guān], Guangdong", "pyn": "Dān xiá shān"}, {"cur": "霞山", "trd": null, "mng": "Xiashan district of Zhanjiang city 湛江市[Zhan4 jiang1 shi4], Guangdong", "pyn": "Xiá shān"}, {"cur": "栖霞区", "trd": "棲霞區", "mng": "Qixia District of Nanjing City 南京市 in Jiangsu 江蘇|江苏", "pyn": "Qī xiá qū"}, {"cur": "伏明霞", "trd": null, "mng": "Fu Mingxia (1978-), Chinese diving champion", "pyn": "Fú Míng xiá"}], "cur": "霞"}