{"hnz": "香", "trd": null, "isTrd": false, "cmp": ["丿 (slash)", "禾 (cereal/grain)", "木 (tree/wood)", "日 (Japan/day/sun/date/day of the month)"], "mng": ["fragrant, sweet smelling, aromatic, savory or appetizing, (to eat) with relish, (of sleep) sound, perfume or spice, joss or incense stick"], "pyn": ["xiāng"], "exm": [{"cur": "香", "trd": null, "mng": "fragrant, sweet smelling, aromatic, savory or appetizing, (to eat) with relish, (of sleep) sound, perfume or spice, joss or incense stick", "pyn": "xiāng"}, {"cur": "香港", "trd": null, "mng": "Hong Kong", "pyn": "Xiāng gǎng"}, {"cur": "古色古香", "trd": null, "mng": "interesting and appealing (of old locations, objects etc)", "pyn": "gǔ sè gǔ xiāng"}, {"cur": "香料", "trd": null, "mng": "spice, flavoring, condiment, perfume", "pyn": "xiāng liào"}, {"cur": "香火", "trd": null, "mng": "incense burning in front of a temple, burning joss sticks", "pyn": "xiāng huǒ"}, {"cur": "芳香", "trd": null, "mng": "balmy, fragrant, aromatic (chemistry)", "pyn": "fāng xiāng"}, {"cur": "香水", "trd": null, "mng": "perfume, cologne", "pyn": "xiāng shuǐ"}, {"cur": "烧香", "trd": "燒香", "mng": "to burn incense", "pyn": "shāo xiāng"}, {"cur": "鸟语花香", "trd": "鳥語花香", "mng": "lit. birdsong and fragrant flowers (idiom); fig. the intoxication of a beautiful spring day", "pyn": "niǎo yǔ huā xiāng"}, {"cur": "麝香", "trd": null, "mng": "musk", "pyn": "shè xiāng"}, {"cur": "香炉", "trd": "香爐", "mng": "a censer (for burning incense), incense burner, thurible", "pyn": "xiāng lú"}, {"cur": "香甜", "trd": null, "mng": "fragrant and sweet, sound (sleep)", "pyn": "xiāng tián"}, {"cur": "茴香", "trd": null, "mng": "fennel (Foeniculum vulgare)", "pyn": "huí xiāng"}, {"cur": "馨香", "trd": null, "mng": "fragrance, fragrant (of incense)", "pyn": "xīn xiāng"}, {"cur": "香皂", "trd": null, "mng": "perfumed soap, toilet soap", "pyn": "xiāng zào"}, {"cur": "口香糖", "trd": null, "mng": "chewing gum", "pyn": "kǒu xiāng táng"}, {"cur": "香喷喷", "trd": "香噴噴", "mng": "delicious, savory", "pyn": "xiāng pēn pēn"}, {"cur": "香味", "trd": null, "mng": "fragrance, bouquet, sweet smell", "pyn": "xiāng wèi"}, {"cur": "吃香", "trd": null, "mng": "very popular", "pyn": "chī xiāng"}, {"cur": "香精", "trd": null, "mng": "seasoning, condiment, flavoring, dressing, essences", "pyn": "xiāng jīng"}], "cur": "香"}