{"hnz": "鳏", "trd": "鰥", "isTrd": false, "cmp": ["鱼 (fish)", "罒 (net)", "眔 (Unknown)", "氺 (water)"], "mng": ["widower"], "pyn": ["guān"], "exm": [{"cur": "鳏夫", "trd": "鰥伕", "mng": "former husband, widower", "pyn": "guān fū"}, {"cur": "鳏居", "trd": "鰥居", "mng": "to live as a widower", "pyn": "guān jū"}, {"cur": "鳏夫", "trd": "鰥夫", "mng": "former husband, widower", "pyn": "guān fū"}, {"cur": "鳏寡孤独", "trd": "鰥寡孤獨", "mng": "lit. widowers, widows, orphans and the childless, fig. people with no one left to rely on", "pyn": "guān guǎ gū dú"}], "cur": "鳏"}