{"hnz": "鸦", "trd": "鵶", "isTrd": false, "cmp": ["牙 (tooth/ivory)", "鸟 (bird)"], "mng": ["crow", "variant of 鴉|鸦[ya1]"], "pyn": ["yā"], "exm": [{"cur": "鸦", "trd": "鴉", "mng": "crow", "pyn": "yā"}, {"cur": "鸦", "trd": "鵶", "mng": "variant of 鴉|鸦[ya1]", "pyn": "yā"}, {"cur": "涂鸦", "trd": "塗鴉", "mng": "graffiti, scrawl, poor calligraphy, to write badly, to scribble", "pyn": "tú yā"}, {"cur": "鸦片", "trd": "鴉片", "mng": "opium (loanword)", "pyn": "yā piàn"}, {"cur": "乌鸦", "trd": "烏鴉", "mng": "crow, raven", "pyn": "wū yā"}, {"cur": "鸦片战争", "trd": "鴉片戰爭", "mng": "the Opium Wars of 1840-1842 and 1860-1861", "pyn": "Yā piàn zhàn zhēng"}, {"cur": "鸦雀无声", "trd": "鴉雀無聲", "mng": "lit. crow and peacock make no sound, absolute silence (idiom); not a single voice can be heard, absolute silence", "pyn": "yā què wú shēng"}, {"cur": "乌鸦嘴", "trd": "烏鴉嘴", "mng": "lit. crow's beak, fig. person who has made an inauspicious remark", "pyn": "wū yā zuǐ"}, {"cur": "渡鸦", "trd": "渡鴉", "mng": "(bird species of China) common raven (Corvus corax)", "pyn": "dù yā"}, {"cur": "大乌鸦", "trd": "大烏鴉", "mng": "a raven", "pyn": "dà wū yā"}, {"cur": "松鸦", "trd": "松鴉", "mng": "(bird species of China) Eurasian jay (Garrulus glandarius)", "pyn": "sōng yā"}, {"cur": "乌鸦座", "trd": "烏鴉座", "mng": "Corvus (constellation)", "pyn": "wū yā zuò"}, {"cur": "水老鸦", "trd": "水老鴉", "mng": "common name for cormorant", "pyn": "shuǐ lǎo yā"}, {"cur": "褐鸦雀", "trd": "褐鴉雀", "mng": "(bird species of China) brown parrotbill (Cholornis unicolor)", "pyn": "hè yā què"}, {"cur": "褐翅鸦鹃", "trd": "褐翅鴉鵑", "mng": "(bird species of China) greater coucal (Centropus sinensis)", "pyn": "hè chì yā juān"}, {"cur": "褐翅鸦雀", "trd": "褐翅鴉雀", "mng": "(bird species of China) brown-winged parrotbill (Sinosuthora brunnea)", "pyn": "hè chì yā què"}, {"cur": "里海地鸦", "trd": "裡海地鴉", "mng": "(bird species of China) Pander's ground jay (Podoces panderi)", "pyn": "Lǐ Hǎi dì yā"}, {"cur": "红头鸦雀", "trd": "紅頭鴉雀", "mng": "(bird species of China) rufous-headed parrotbill (Psittiparus bakeri)", "pyn": "hóng tóu yā què"}, {"cur": "红嘴鸦雀", "trd": "紅嘴鴉雀", "mng": "(bird species of China) great parrotbill (Conostoma oemodium)", "pyn": "hóng zuǐ yā què"}, {"cur": "红嘴山鸦", "trd": "紅嘴山鴉", "mng": "(bird species of China) red-billed chough (Pyrrhocorax pyrrhocorax)", "pyn": "hóng zuǐ shān yā"}], "cur": "鸦"}